hammer_sh/__init__.py
hammer_sh/doc2vec.py
hammer_sh/evaluator.py
hammer_sh/model_trainer.py
hammer_sh/pdf_extractor.py
hammer_sh/preprocessor.py
hammer_sh/web_scraper.py
hammer_sh/sample_data/abstracts.pickle
hammer_sh/sample_data/articles.pickle
hammer_sh-0.0.18.dist-info/LICENSE
hammer_sh-0.0.18.dist-info/METADATA
hammer_sh-0.0.18.dist-info/WHEEL
hammer_sh-0.0.18.dist-info/top_level.txt
hammer_sh-0.0.18.dist-info/RECORD
